atc_api/__init__.py
atc_api/atcd_client.py
atc_api/serializers.py
atc_api/settings.py
atc_api/urls.py
atc_api/utils.py
atc_api/views.py
atc_api/static/js/atc-api.js
django_atc_api-0.1.6.dist-info/DESCRIPTION.rst
django_atc_api-0.1.6.dist-info/METADATA
django_atc_api-0.1.6.dist-info/RECORD
django_atc_api-0.1.6.dist-info/WHEEL
django_atc_api-0.1.6.dist-info/metadata.json
django_atc_api-0.1.6.dist-info/top_level.txt
