Metadata-Version: 2.0
Name: django-atc-api
Version: 0.1.6
Summary: REST API for ATC
Home-page: https://github.com/facebook/augmented-traffic-control
Author: Emmanuel Bretelle
Author-email: chantra@fb.com
License: UNKNOWN
Platform: UNKNOWN
Classifier: Programming Language :: Python
Requires-Dist: atc-thrift
Requires-Dist: djangorestframework
